silvimetric/__init__.py
silvimetric/cli/__init__.py
silvimetric/cli/cli.py
silvimetric/cli/common.py
silvimetric/commands/__init__.py
silvimetric/commands/extract.py
silvimetric/commands/info.py
silvimetric/commands/initialize.py
silvimetric/commands/manage.py
silvimetric/commands/scan.py
silvimetric/commands/shatter.py
silvimetric/resources/__init__.py
silvimetric/resources/array_extensions.py
silvimetric/resources/attribute.py
silvimetric/resources/bounds.py
silvimetric/resources/config.py
silvimetric/resources/constants.py
silvimetric/resources/data.py
silvimetric/resources/extents.py
silvimetric/resources/log.py
silvimetric/resources/metric.py
silvimetric/resources/names.py
silvimetric/resources/storage.py
silvimetric/resources/taskgraph.py
silvimetric/resources/metrics/__init__.py
silvimetric/resources/metrics/aad.py
silvimetric/resources/metrics/counts.py
silvimetric/resources/metrics/covers.py
silvimetric/resources/metrics/filters.py
silvimetric/resources/metrics/grid_metrics.py
silvimetric/resources/metrics/l_moments.py
silvimetric/resources/metrics/p_moments.py
silvimetric/resources/metrics/percentiles.py
silvimetric/resources/metrics/stats.py
silvimetric-1.4.0.dist-info/licenses/LICENSE.txt
silvimetric-1.4.0.dist-info/METADATA
silvimetric-1.4.0.dist-info/WHEEL
silvimetric-1.4.0.dist-info/entry_points.txt
silvimetric-1.4.0.dist-info/top_level.txt
silvimetric-1.4.0.dist-info/RECORD
