Metadata-Version: 2.4
Name: silvimetric
Version: 1.4.0
Summary: A forestry LiDAR processing package
Author-email: Kyle Mann <kyle@hobu.co>, Howard Butler <howard@hobu.co>
Maintainer-email: Kyle Mann <kyle@hobu.co>
License: Apache-2.0
Project-URL: homepage, https://github.com/hobuinc/silvimetric
Project-URL: repository, https://github.com/hobuinc/silvimetric
Classifier: Development Status :: 4 - Beta
Classifier: Intended Audience :: Information Technology
Classifier: Intended Audience :: Science/Research
Classifier: License :: OSI Approved :: Apache Software License
Classifier: Topic :: Scientific/Engineering :: GIS
Classifier: Topic :: Scientific/Engineering :: Image Processing
Requires-Python: >=3.9
License-File: LICENSE.txt
Dynamic: license-file
